LICENSE
README.md
setup.py
eospy/__init__.py
eospy/__version__.py
eospy/cleos.py
eospy/command_line.py
eospy/dynamic_url.py
eospy/exceptions.py
eospy/keys.py
eospy/schema.py
eospy/signer.py
eospy/testeos.py
eospy/types.py
eospy/utils.py
libeospy.egg-info/PKG-INFO
libeospy.egg-info/SOURCES.txt
libeospy.egg-info/dependency_links.txt
libeospy.egg-info/entry_points.txt
libeospy.egg-info/requires.txt
libeospy.egg-info/top_level.txt