Metadata-Version: 2.1
Name: libeospy
Version: 2.1.0
Summary: Python library for the eos.io REST API
Home-page: https://github.com/eosnewyork/eospy
Author: deck
Author-email: deck@eosnewyork.io
License: UNKNOWN
Platform: UNKNOWN
License-File: LICENSE
